RequestsLogger.py
robotframework_requestslogger-2.0.0.dist-info/LICENSE
robotframework_requestslogger-2.0.0.dist-info/METADATA
robotframework_requestslogger-2.0.0.dist-info/WHEEL
robotframework_requestslogger-2.0.0.dist-info/top_level.txt
robotframework_requestslogger-2.0.0.dist-info/RECORD
