Metadata-Version: 1.1
Name: robotframework-requestslogger
Version: 2.0.0
Summary: Robot Framework Requests Logging Library
Home-page: https://github.com/peterservice-rnd/robotframework-requestslogger
Author: JSC PETER-SERVICE
Author-email: mf_aist_all@billing.ru
License: Apache License 2.0
Keywords: testing testautomation robotframework logging autotest requests http
Platform: UNKNOWN
Classifier: Development Status :: 5 - Production/Stable
Classifier: Intended Audience :: Developers
Classifier: Topic :: Software Development :: Testing
Classifier: License :: OSI Approved :: Apache Software License
Classifier: Programming Language :: Python :: 3.5
Classifier: Programming Language :: Python :: 3.6
Classifier: Framework :: Robot Framework :: Library
